fd_mcp/__init__.py
fd_mcp/server.py
fd_mcp-0.2.4.dist-info/licenses/LICENSE
fd_mcp-0.2.4.dist-info/METADATA
fd_mcp-0.2.4.dist-info/WHEEL
fd_mcp-0.2.4.dist-info/entry_points.txt
fd_mcp-0.2.4.dist-info/top_level.txt
fd_mcp-0.2.4.dist-info/RECORD
