Metadata-Version: 2.4
Name: fd-mcp
Version: 0.2.4
Summary: MCP server for fast file search using fd - a modern find alternative
Author: Thomas Hartwig
License-Expression: MIT
Project-URL: Homepage, https://github.com/thhart/fd-mcp
Project-URL: Repository, https://github.com/thhart/fd-mcp
Project-URL: Issues, https://github.com/thhart/fd-mcp/issues
Keywords: mcp,fd,file-search,ai,claude,model-context-protocol
Classifier: Development Status :: 4 - Beta
Classifier: Intended Audience :: Developers
Classifier: Programming Language :: Python :: 3
Classifier: Programming Language :: Python :: 3.10
Classifier: Programming Language :: Python :: 3.11
Classifier: Programming Language :: Python :: 3.12
Classifier: Topic :: Software Development :: Libraries :: Python Modules
Requires-Python: >=3.10
License-File: LICENSE
Requires-Dist: mcp>=1.0.0
Dynamic: license-file
